{
    "description": "Get ready, everyone! The match kicks off at 5:45 PM on Thursday, November 7, 2024!",
    "match_date": "2024-11-07",
    "match_time": "05:45 PM (UTC Time)",
    "match_day": "Thursday",
    "odds": {
        "home": 3.1,
        "draw": 3.3,
        "away": 2.35
    },
    "word_count": 15,
    "reading_time": 6.06,
    "home_team": {
        "name": "Fotbal Club FCSB",
        "logo": "https://img.thesports.com/football/team/a413daa882f96b18ddb1f0e8c9dbfda7.png",
        "country": "Romania"
    },
    "away_team": {
        "name": "Midtjylland",
        "logo": "https://img.thesports.com/football/team/870815ca7c7545f7dc8c0716eecdb708.png",
        "country": "Denmark"
    }
}