{
    "description": "And the last match: OGC Nice versus LOSC Lille. What a thriller! Goals, drama, tension!",
    "word_count": 15,
    "reading_time": 6.31,
    "home_team": {
        "name": "OGC Nice",
        "logo": "https://img.thesports.com/football/team/ff8991853f7aabce7cb66f09cda0c58e.png",
        "country": "France"
    },
    "away_team": {
        "name": "LOSC Lille",
        "logo": "https://img.thesports.com/football/team/28e94925fdcc848f86a544a1cedcceed.png",
        "country": "France"
    }
}