{
    "description": "The home team struggles continue with no wins in five matches, while the away side, slightly better, scraped a win in their last five outings.",
    "recent_form": {
        "home_team": {
            "last_5_matches": [
                "l",
                "d",
                "l",
                "l",
                "d"
            ],
            "wins": 0,
            "draws": 2,
            "losses": 3
        },
        "away_team": {
            "last_5_matches": [
                "l",
                "l",
                "d",
                "l",
                "w"
            ],
            "wins": 1,
            "draws": 1,
            "losses": 3
        }
    }
}